mcp_server_dnspod/__init__.py
mcp_server_dnspod/capi_client.py
mcp_server_dnspod/server.py
mcp_server_dnspod/tool_dnspod.py
mcp_server_dnspod-0.1.8.dist-info/METADATA
mcp_server_dnspod-0.1.8.dist-info/WHEEL
mcp_server_dnspod-0.1.8.dist-info/entry_points.txt
mcp_server_dnspod-0.1.8.dist-info/RECORD
