Metadata-Version: 2.4
Name: mcp-server-dnspod
Version: 0.1.8
Summary: MCP Server for Tencent Cloud DNSPod
Requires-Python: >=3.10
Requires-Dist: mcp>=1.0.0
Requires-Dist: tencentcloud-sdk-python-common==3.0.1375
Requires-Dist: tencentcloud-sdk-python-dnspod==3.0.1375
